{
    "id": "skill-combat-leather-01-02",
    "name": "Slashing Resistance",
    "tree": "Leather",
    "maxPoints": 5,
    "pointRequirement": 0,
    "pipAmount": 21960,
    "description": "Increases Slashing Resistance while using Leather chest armor.",
    "icon": "skill-combat-leather-01-02.png",
    "stats": [
        {
            "name": "Slashing Resistance",
            "amount": "60"
        }
    ],
    "grants": [],
    "unlockedFromSkill": [
        {
            "skill": "skill-combat-leather-01-01",
            "point": 4
        },
        {
            "skill": "skill-combat-leather-01-03",
            "point": 4
        }
    ],
    "unlocksSkill": [
        "skill-combat-leather-01-03"
    ]
}