{
    "id": "skill-generic-exploration-327",
    "name": "Grave Specialization",
    "tree": "Grave Specialization",
    "maxPoints": 5,
    "pointRequirement": 0,
    "pipAmount": 18000,
    "description": "Decreases the amount of Decay that Runestone Shovels suffer when digging. Also Beneficial Harvests from digging can now apply temporary Buff Effects to you.",
    "icon": "skill-generic-exploration-327.png",
    "stats": [
        {
            "name": "Decay Reduction: Shovels",
            "amount": "1%"
        },
        {
            "name": "Beneficial Harvest Effects: Grave",
            "amount": "0.2%"
        }
    ],
    "grants": [],
    "unlockedFromSkill": [],
    "unlocksSkill": [
        "skill-generic-exploration-328",
        "skill-generic-exploration-329",
        "skill-generic-exploration-321",
        "skill-generic-exploration-330",
        "skill-generic-exploration-331"
    ]
}