{
    "id": "myrmidon-arcing-slash",
    "name": "Arcing Slash",
    "class": "myrmidon",
    "description": "This talent grants the Arcing Slash power.",
    "icon": "arcing-slash.png",
    "maxPoints": 1,
    "pointRequirement": 0,
    "levelRequirement": 0,
    "grants": [
        {
            "id": "myrmidon-arcing-slash",
            "name": "Arcing Slash"
        }
    ],
    "unlockedFromSkill": [
        {
            "skill": "myrmidon-shredded",
            "point": 1
        },
        {
            "skill": "myrmidon-additional-minor-slot",
            "point": 1
        },
        {
            "skill": "myrmidon-powerhouse",
            "point": 1
        }
    ],
    "unlocksSkill": [
        "myrmidon-cast-net"
    ],
    "locksSkill": []
}