{
    "id": "daring-escape",
    "name": "Daring Escape",
    "class": "duelist",
    "description": "Daring Escape enhances Retaliate powers to recover 35 Stamina over 7 seconds.",
    "icon": "Skill_Icon_034_009.png",
    "pointRequirement": 0,
    "levelRequirement": 0,
    "grants": [],
    "unlockedFromSkill": [
        {
            "skill": "lurk-more",
            "point": 2
        }
    ],
    "unlocksSkill": [
        "fast-tunneling",
        "cheap-shots"
    ],
    "locksSkill": []
}