{
  "classes": [
    "assassin",
    "druid",
    "frostweaver"
  ],
  "description": "Once a playful and joyous folk, the Fae have developed an interesting method of population control many do not understand.",
  "name": "Fae",
  "tags": [],
  "powers": [
    "fae-bloodline",
    "dodge-fae",
    "faerie-fire"
  ],
  "slots_granted": [],
  "slots_removed": [],
  "type": "race",
  "stats": [{
      "name": "Dexterity",
      "value": 30
    },
    {
      "name": "Intellect",
      "value": 30
    },
    {
      "name": "Strength Cap",
      "value": -50
    },
    {
      "name": "Dexterity Cap",
      "value": 100
    },
    {
      "name": "Constitution Cap",
      "value": -50
    }
  ],
  "equips": [],
  "tray_granted": "",
  "tray_removed": ""
}