{
    "id": "knight-pell-training",
    "name": "Pell Training",
    "class": "knight",
    "description": "Stat Adjustments:\\nEnergy +225\\nStamina +15\\n\\n\"Tarry not, and whatever you do, do not hesitate your blade.\"\\n-Anonymous",
    "icon": "pell-training.png",
    "maxPoints": 1,
    "pointRequirement": 0,
    "levelRequirement": 0,
    "grants": [],
    "unlockedFromSkill": [
        {
            "skill": "knight-noble-blood",
            "point": 1
        },
        {
            "skill": "knight-shield-bash",
            "point": 1
        },
        {
            "skill": "knight-additional-minor-slot",
            "point": 1
        }
    ],
    "unlocksSkill": [
        "knight-additional-minor-slot",
        "knight-pursuit",
        "knight-resolve"
    ],
    "locksSkill": []
}