{
    "id": "ultimate-warrior",
    "name": "Ultimate Warrior",
    "class": "champion",
    "description": "This talent grants the Ultimate Warrior power.",
    "icon": "ultimate-warrior.png",
    "pointRequirement": 0,
    "levelRequirement": 0,
    "grants": [
        {
            "id": "ultimate-warrior",
            "name": "Ultimate Warrior"
        }
    ],
    "unlockedFromSkill": [
        {
            "skill": "toughness",
            "point": 3
        }
    ],
    "unlocksSkill": [
        "fortification"
    ],
    "locksSkill": []
}