{
    "id": "confessor-fervor",
    "name": "Fervor",
    "description": "restores 350 Mana over five seconds and reduce your physical mitigations by 15% while channeling.",
    "shortDescription": "",
    "icon": "confessor-fervor.png",
    "stats": {
        "duration": "5 seconds",
        "restore_type_time": "over five seconds",
        "restore_type": "Mana",
        "restore": "350",
        "cooldown": "45",
        "target": "Self",
        "cast_time": "Channeled"
    },
    "nextChain": [],
    "lastChain": [],
    "inSpellbook": true,
    "isGroupPower": false,
    "isBeneficial": false,
    "isHeal": false,
    "isBuff": false,
    "tags": [
        "confessor"
    ]
}