{
    "id": "daggermaster-slow-demise-1",
    "name": "Slow Demise",
    "description": "hits an enemy for 75 - 112 + 93% Weapon Damage.",
    "shortDescription": "Attack: Reduces the amount an enemy can be healed and inflicts a large amount of damage.",
    "icon": "daggermaster-slow-demise-1.png",
    "stats": {
        "weapon_damage_value": "93",
        "max_damage_1": "112",
        "min_damage_1": "75",
        "cost_type": "Resource",
        "cost": "11",
        "range": "6",
        "max_targets": "1",
        "cooldown": "9",
        "target": "Cone",
        "cast_time": "Instant"
    },
    "nextChain": [
        "daggermaster-slow-demise-2"
    ],
    "lastChain": [],
    "inSpellbook": true,
    "isGroupPower": false,
    "isBeneficial": false,
    "isHeal": false,
    "isBuff": false,
    "tags": [
        "melee"
    ]
}