{
    "id": "furious-dmg-bonus-full-rage",
    "name": "Furious",
    "description": "increases your Damage Bonus by 10% for 15 seconds when reaching 100 Rage.",
    "shortDescription": "Passive: Increase Damage Bonus if Rage hits max",
    "icon": "furious-dmg-bonus-full-rage.png",
    "stats": {
        "buff_amount_1": "10%",
        "buff_type_1": "Damage Bonus",
        "duration": "15 seconds",
        "target": "Self",
        "cast_time": "Passive"
    },
    "nextChain": [],
    "lastChain": [],
    "inSpellbook": true,
    "isGroupPower": false,
    "isBeneficial": false,
    "isHeal": false,
    "isBuff": false,
    "tags": [
        "anyone"
    ]
}