{
    "id": "minor-accompaniment",
    "name": "Minor Accompaniment",
    "description": "increases your Song Damage by 20%.",
    "shortDescription": "Passive: Increase Song Damage",
    "icon": "Graphic_Disc_MinorAccompaniment.png",
    "stats": {
        "cast_time": "Passive",
        "target": "Self",
        "buff_type_1": "Song Damage",
        "buff_amount_1": "20%"
    },
    "nextChain": [],
    "lastChain": [],
    "inSpellbook": true,
    "isGroupPower": false,
    "isBeneficial": false,
    "isHeal": false,
    "isBuff": false,
    "tags": [
        "anyone"
    ]
}