{
    "cast_type": "passive",
    "cooldown": 0,
    "cost": [],
    "duration": 0,
    "max_targets": 0,
    "name": "Mortal Sin",
    "next_chain": [],
    "previous_chain": [],
    "range": 0,
    "sources": [
        {
            "id": "mortal-sin",
            "type": "discipline"
        }
    ],
    "tags": [
        "Sin"
    ],
    "targeting": "self",
    "type": "passive",
    "description": "You now apply Mortal Sin instead of Sin.  For each stack of Mortal Sin the target becomes more vulnerable to being Critically Hit by 2% per stack.  All powers that require Sin will also benefit from Mortal Sin."
}