{
    "cast_type": "instant",
    "cooldown": 45,
    "cost": [
        {
            "name": "resource",
            "cost": 16
        }
    ],
    "duration": 20,
    "max_targets": 0,
    "name": "Thornshield",
    "next_chain": [],
    "previous_chain": [],
    "range": 0,
    "sources": [
        {
            "id": "thornshield",
            "data_type": "discipline"
        }
    ],
    "tags": [],
    "targeting": "self",
    "type": "buff",
    "description": "Envelope yourself with dangerous Thorns for 20 seconds causing any who strike you to take damage."
}