{
    "id": "butcher",
    "name": "Butcher",
    "type": "major",
    "trait": [
        {
            "id": "trait-war-or-battle",
            "name": "War or Battle"
        }
    ],
    "icon": "butcher.png",
    "stats": [
        {
            "name": "Movement Speed: Trailblazer",
            "value": "15%"
        },
        {
            "name": "Slashing Damage Bonus",
            "value": "2%"
        }
    ],
    "grantsPowers": [
        "knifegrinder-bleed-debuff-1",
        "banshee-angel-of-death"
    ],
    "grantsSlot": [],
    "grantsTrait": [],
    "description": ".",
    "lore": "."
}
