{
    "id": "kanes-apostle",
    "name": "Kane's Apostle",
    "type": "major",
    "trait": [
        {
            "id": "trait-justice",
            "name": "Justice"
        }
    ],
    "icon": "kanes-apostle.png",
    "stats": [
        {
            "name": "Armor Penetration: Crushing",
            "value": "3%"
        },
        {
            "name": "Crushing Damage Bonus",
            "value": "2%"
        }
    ],
    "grantsPowers": [
        "runecaster-fortification",
        "power_discipline_demolisher_cracked_armor"
    ],
    "grantsSlot": [],
    "grantsTrait": [],
    "description": ".",
    "lore": "."
}
