{
    "id": "skill-combat-mail-04-05",
    "name": "Pathfinding",
    "tree": "Mail",
    "maxPoints": 5,
    "pointRequirement": 0,
    "pipAmount": 23040,
    "description": "Increases Pathfinding while using Mail chest armor.",
    "icon": "skill-combat-mail-04-05.png",
    "stats": [
        {
            "name": "Pathfinding",
            "amount": "2%"
        }
    ],
    "grants": [],
    "unlockedFromSkill": [
        {
            "skill": "skill-combat-mail-04-01",
            "point": 4
        },
        {
            "skill": "skill-combat-mail-04-04",
            "point": 4
        }
    ],
    "unlocksSkill": [
        "skill-combat-mail-04-04"
    ]
}