{
  "cast_type": "Toggle",
  "cooldown": 1,
  "cost": {
    "pips": 0,
    "resource": 0
  },
  "duration": 12,
  "icon": "https://cdn.malekai.network/images/powers/guardian-rhythms.png",
  "max_targets": 5,
  "name": "Guardian Rhythms",
  "next_chain": [],
  "previous_chain": [],
  "range": 0,
  "sources": [
    {
      "id": "bard",
      "sub_type": "major",
      "type": "discipline"
    }
  ],
  "targeting": "Group",
  "tooltip": "Reduces the groups Damage Taken by 15% for 12 seconds. Type 2 Song.",
  "type": "Buff"
}
