{
  "cast_type": "Passive",
  "cooldown": 0,
  "cost": {
    "pips": 0,
    "resource": 0
  },
  "duration": 0,
  "icon": "https://cdn.malekai.network/images/powers/molon-labe.png",
  "max_targets": 0,
  "name": "Molon Labe",
  "next_chain": [],
  "previous_chain": [],
  "range": 0,
  "sources": [
    {
      "id": "shield-fighter",
      "sub_type": "major",
      "type": "discipline"
    }
  ],
  "targeting": "Self",
  "tooltip": "Block high damage attacks with reduced cost and a 5% increase in bonus damage for 2 additional seconds.",
  "type": "Passive"
}
