{
    "id": "ranger-treant-lore",
    "name": "Treant Lore",
    "class": "ranger",
    "description": "Treant Lore enhances Archers Stake to become Treant Wood Stake, which removes its deploy time and reduces all Damage Taken by 15%.",
    "icon": "treant-lore.png",
    "maxPoints": 1,
    "pointRequirement": 0,
    "levelRequirement": 0,
    "grants": [
        {
            "id": "treant-wood-stake",
            "name": "Treant Wood Stake"
        }
    ],
    "unlockedFromSkill": [
        {
            "skill": "ranger-ravencoat",
            "point": 1
        }
    ],
    "unlocksSkill": [
        "ranger-tree-sap-blood"
    ],
    "locksSkill": []
}